setup.py
flatpages_index/__init__.py
flatpages_index/flatpages.py
flatpages_index/utils.py
flatpages_index.egg-info/PKG-INFO
flatpages_index.egg-info/SOURCES.txt
flatpages_index.egg-info/dependency_links.txt
flatpages_index.egg-info/not-zip-safe
flatpages_index.egg-info/requires.txt
flatpages_index.egg-info/top_level.txt