Metadata-Version: 1.0
Name: flatpages-index
Version: 0.1
Summary: A small extension for flask_flatpages
Home-page: UNKNOWN
Author: Andreas Stephanides
Author-email: st-andreas@gmx.at
License: UNKNOWN
Platform: UNKNOWN
